AIscientists/__init__.py
AIscientists/auth.py
AIscientists/config.py
AIscientists/main.py
AIscientists/setup.py
AIscientists/pyarmor_runtime_007070/__init__.py
AIscientists-0.1.1.dist-info/METADATA
AIscientists-0.1.1.dist-info/WHEEL
AIscientists-0.1.1.dist-info/entry_points.txt
AIscientists-0.1.1.dist-info/top_level.txt
AIscientists-0.1.1.dist-info/RECORD
