Metadata-Version: 2.1
Name: AIscientists
Version: 0.1.1
Summary: AIscientists package for automated data science workflow.
Author: AI Scientists
Author-email: support@AIscientists.ai
Classifier: Programming Language :: Python :: 3
Classifier: License :: OSI Approved :: MIT License
Classifier: Operating System :: OS Independent
Requires-Dist: requests
Requires-Dist: python-dotenv
